[
  {
    "x": 0.023718,
    "y": -0.9232,
    "z": -3.506454,
    "visibility": 0.999998
  },
  {
    "x": 0.02846,
    "y": -0.988302,
    "z": -3.24676,
    "visibility": 0.99999
  },
  {
    "x": 0.033966,
    "y": -0.987655,
    "z": -3.247221,
    "visibility": 0.999993
  },
  {
    "x": 0.040136,
    "y": -0.987034,
    "z": -3.247651,
    "visibility": 0.99999
  },
  {
    "x": 0.007716,
    "y": -0.992192,
    "z": -3.322056,
    "visibility": 0.999985
  },
  {
    "x": -0.002818,
    "y": -0.992161,
    "z": -3.321675,
    "visibility": 0.999984
  },
  {
    "x": -0.012854,
    "y": -0.991179,
    "z": -3.32112,
    "visibility": 0.999972
  },
  {
    "x": 0.04097,
    "y": -0.957685,
    "z": -1.719763,
    "visibility": 0.999983
  },
  {
    "x": -0.03348,
    "y": -0.950308,
    "z": -2.057049,
    "visibility": 0.999976
  },
  {
    "x": 0.031789,
    "y": -0.842736,
    "z": -2.93562,
    "visibility": 0.999996
  },
  {
    "x": 0.004745,
    "y": -0.843458,
    "z": -3.032332,
    "visibility": 0.999996
  },
  {
    "x": 0.108654,
    "y": -0.519293,
    "z": -0.578389,
    "visibility": 0.999998
  },
  {
    "x": -0.109559,
    "y": -0.480707,
    "z": -1.209968,
    "visibility": 0.999958
  },
  {
    "x": 0.207315,
    "y": -0.143837,
    "z": -0.944225,
    "visibility": 0.99682
  },
  {
    "x": -0.148043,
    "y": 0.088904,
    "z": -1.061979,
    "visibility": 0.994031
  },
  {
    "x": 0.334232,
    "y": -0.222041,
    "z": -3.510144,
    "visibility": 0.998775
  },
  {
    "x": -0.146602,
    "y": 0.555416,
    "z": -2.04113,
    "visibility": 0.988628
  },
  {
    "x": 0.374422,
    "y": -0.27489,
    "z": -4.027001,
    "visibility": 0.995973
  },
  {
    "x": -0.162432,
    "y": 0.726491,
    "z": -2.286184,
    "visibility": 0.969698
  },
  {
    "x": 0.370398,
    "y": -0.323471,
    "z": -4.376715,
    "visibility": 0.996792
  },
  {
    "x": -0.140744,
    "y": 0.726978,
    "z": -2.669095,
    "visibility": 0.97209
  },
  {
    "x": 0.357165,
    "y": -0.308537,
    "z": -3.72369,
    "visibility": 0.995585
  },
  {
    "x": -0.129331,
    "y": 0.674097,
    "z": -2.196049,
    "visibility": 0.962728
  },
  {
    "x": 0.062384,
    "y": 0.491005,
    "z": 0.320718,
    "visibility": 0.999957
  },
  {
    "x": -0.06148,
    "y": 0.508995,
    "z": -0.320819,
    "visibility": 0.999746
  },
  {
    "x": 0.162713,
    "y": 1.18354,
    "z": -1.920788,
    "visibility": 0.989663
  },
  {
    "x": -0.023074,
    "y": 1.235013,
    "z": -0.992704,
    "visibility": 0.987695
  },
  {
    "x": 0.144893,
    "y": 1.993231,
    "z": -0.178511,
    "visibility": 0.988044
  },
  {
    "x": -0.013324,
    "y": 1.964025,
    "z": 1.116173,
    "visibility": 0.980251
  },
  {
    "x": 0.118309,
    "y": 2.066283,
    "z": -0.101315,
    "visibility": 0.931081
  },
  {
    "x": -0.006993,
    "y": 2.044593,
    "z": 1.232779,
    "visibility": 0.769394
  },
  {
    "x": 0.190173,
    "y": 2.333638,
    "z": -1.803809,
    "visibility": 0.9808
  },
  {
    "x": -0.017437,
    "y": 2.241645,
    "z": -0.367729,
    "visibility": 0.973732
  }
]