[
  {
    "x": -0.053263,
    "y": -0.857486,
    "z": -1.411459,
    "visibility": 0.9998
  },
  {
    "x": 0.017831,
    "y": -0.93302,
    "z": -1.340983,
    "visibility": 0.9995
  },
  {
    "x": 0.053196,
    "y": -0.934471,
    "z": -1.343321,
    "visibility": 0.9995
  },
  {
    "x": 0.105362,
    "y": -0.936159,
    "z": -1.343224,
    "visibility": 0.9997
  },
  {
    "x": -0.136352,
    "y": -0.931296,
    "z": -1.338593,
    "visibility": 0.9996
  },
  {
    "x": -0.173145,
    "y": -0.929805,
    "z": -1.341957,
    "visibility": 0.9997
  },
  {
    "x": -0.203797,
    "y": -0.929365,
    "z": -1.343511,
    "visibility": 0.9997
  },
  {
    "x": 0.154272,
    "y": -0.910625,
    "z": -0.702374,
    "visibility": 0.9999
  },
  {
    "x": -0.256023,
    "y": -0.8966,
    "z": -0.683804,
    "visibility": 0.9995
  },
  {
    "x": 0.042393,
    "y": -0.788662,
    "z": -1.125982,
    "visibility": 0.9999
  },
  {
    "x": -0.121781,
    "y": -0.78018,
    "z": -1.139382,
    "visibility": 0.9999
  },
  {
    "x": 0.538195,
    "y": -0.536119,
    "z": -0.210856,
    "visibility": 1.0
  },
  {
    "x": -0.569968,
    "y": -0.463881,
    "z": -0.166689,
    "visibility": 0.9999
  },
  {
    "x": 0.967235,
    "y": -0.139094,
    "z": -0.171325,
    "visibility": 0.965
  },
  {
    "x": -1.021034,
    "y": -0.066313,
    "z": -0.463683,
    "visibility": 0.8945
  },
  {
    "x": 0.725918,
    "y": 0.119603,
    "z": -1.072814,
    "visibility": 0.9785
  },
  {
    "x": -0.640558,
    "y": 0.084247,
    "z": -1.734083,
    "visibility": 0.9539
  },
  {
    "x": 0.617959,
    "y": 0.171218,
    "z": -1.310742,
    "visibility": 0.9772
  },
  {
    "x": -0.559515,
    "y": 0.092139,
    "z": -2.047359,
    "visibility": 0.9646
  },
  {
    "x": 0.568316,
    "y": 0.09004,
    "z": -1.415842,
    "visibility": 0.9791
  },
  {
    "x": -0.519348,
    "y": 0.030971,
    "z": -2.088807,
    "visibility": 0.9661
  },
  {
    "x": 0.584923,
    "y": 0.079956,
    "z": -1.116472,
    "visibility": 0.9708
  },
  {
    "x": -0.526666,
    "y": 0.018482,
    "z": -1.781773,
    "visibility": 0.9506
  },
  {
    "x": 0.365819,
    "y": 0.501999,
    "z": 0.006666,
    "visibility": 0.9999
  },
  {
    "x": -0.334046,
    "y": 0.498001,
    "z": -0.008787,
    "visibility": 0.9998
  },
  {
    "x": 0.314913,
    "y": 1.267097,
    "z": -0.085883,
    "visibility": 0.8842
  },
  {
    "x": -0.086097,
    "y": 1.246348,
    "z": -0.216617,
    "visibility": 0.8671
  },
  {
    "x": 0.358315,
    "y": 2.063549,
    "z": 0.529226,
    "visibility": 0.9393
  },
  {
    "x": 0.056066,
    "y": 1.940008,
    "z": 0.664464,
    "visibility": 0.9095
  },
  {
    "x": 0.337011,
    "y": 2.104582,
    "z": 0.541974,
    "visibility": 0.7105
  },
  {
    "x": 0.102222,
    "y": 1.982777,
    "z": 0.732601,
    "visibility": 0.5717
  },
  {
    "x": 0.291028,
    "y": 2.388125,
    "z": -0.398724,
    "visibility": 0.9382
  },
  {
    "x": 0.143875,
    "y": 2.289276,
    "z": -0.085985,
    "visibility": 0.8939
  }
]