[
  {
    "x": 0.045302,
    "y": -0.907973,
    "z": -1.100113,
    "visibility": 0.9981
  },
  {
    "x": 0.145954,
    "y": -0.961521,
    "z": -0.961145,
    "visibility": 0.9969
  },
  {
    "x": 0.204656,
    "y": -0.954585,
    "z": -0.964057,
    "visibility": 0.9963
  },
  {
    "x": 0.265572,
    "y": -0.947572,
    "z": -0.964556,
    "visibility": 0.997
  },
  {
    "x": -0.008854,
    "y": -0.974548,
    "z": -0.892111,
    "visibility": 0.9984
  },
  {
    "x": -0.071071,
    "y": -0.973733,
    "z": -0.897043,
    "visibility": 0.9984
  },
  {
    "x": -0.127736,
    "y": -0.970566,
    "z": -0.900329,
    "visibility": 0.9989
  },
  {
    "x": 0.349474,
    "y": -0.927002,
    "z": -0.102288,
    "visibility": 0.9983
  },
  {
    "x": -0.166795,
    "y": -0.932648,
    "z": 0.199125,
    "visibility": 0.9984
  },
  {
    "x": 0.154717,
    "y": -0.833248,
    "z": -0.74869,
    "visibility": 0.9989
  },
  {
    "x": -0.080868,
    "y": -0.847423,
    "z": -0.691537,
    "visibility": 0.9992
  },
  {
    "x": 0.72609,
    "y": -0.536492,
    "z": -0.200625,
    "visibility": 0.9998
  },
  {
    "x": -0.593738,
    "y": -0.463508,
    "z": 0.988255,
    "visibility": 0.9998
  },
  {
    "x": 0.405367,
    "y": -0.066838,
    "z": -1.438677,
    "visibility": 0.987
  },
  {
    "x": -0.725606,
    "y": 0.066707,
    "z": 0.941079,
    "visibility": 0.7879
  },
  {
    "x": 0.315409,
    "y": -0.584116,
    "z": -2.827531,
    "visibility": 0.9917
  },
  {
    "x": -0.96933,
    "y": 0.543838,
    "z": -0.11772,
    "visibility": 0.8581
  },
  {
    "x": 0.225875,
    "y": -0.709189,
    "z": -3.158103,
    "visibility": 0.9855
  },
  {
    "x": -0.996273,
    "y": 0.708349,
    "z": -0.30499,
    "visibility": 0.7993
  },
  {
    "x": 0.257314,
    "y": -0.760494,
    "z": -3.126568,
    "visibility": 0.9845
  },
  {
    "x": -1.00321,
    "y": 0.713184,
    "z": -0.600902,
    "visibility": 0.807
  },
  {
    "x": 0.261455,
    "y": -0.701954,
    "z": -2.823645,
    "visibility": 0.9755
  },
  {
    "x": -0.957347,
    "y": 0.653501,
    "z": -0.280641,
    "visibility": 0.8129
  },
  {
    "x": 0.338044,
    "y": 0.507214,
    "z": -0.358434,
    "visibility": 0.9999
  },
  {
    "x": -0.470397,
    "y": 0.492786,
    "z": 0.356034,
    "visibility": 0.9999
  },
  {
    "x": 0.482286,
    "y": 1.454554,
    "z": -0.328345,
    "visibility": 0.9538
  },
  {
    "x": -0.436867,
    "y": 1.246983,
    "z": 0.065742,
    "visibility": 0.8369
  },
  {
    "x": 0.709055,
    "y": 2.18711,
    "z": 0.752909,
    "visibility": 0.9498
  },
  {
    "x": -0.15434,
    "y": 1.975645,
    "z": 1.954224,
    "visibility": 0.779
  },
  {
    "x": 0.710697,
    "y": 2.230239,
    "z": 0.793555,
    "visibility": 0.5772
  },
  {
    "x": -0.072478,
    "y": 2.029852,
    "z": 2.09619,
    "visibility": 0.3915
  },
  {
    "x": 0.595365,
    "y": 2.551878,
    "z": -0.605717,
    "visibility": 0.895
  },
  {
    "x": -0.189635,
    "y": 2.32464,
    "z": 1.011724,
    "visibility": 0.6741
  }
]