[
  {
    "x": 0.035846,
    "y": -0.910716,
    "z": -2.403878,
    "visibility": 1.0
  },
  {
    "x": 0.10449,
    "y": -0.975035,
    "z": -2.245714,
    "visibility": 1.0
  },
  {
    "x": 0.137375,
    "y": -0.9741,
    "z": -2.248666,
    "visibility": 1.0
  },
  {
    "x": 0.186228,
    "y": -0.971436,
    "z": -2.248755,
    "visibility": 1.0
  },
  {
    "x": -0.025727,
    "y": -0.980864,
    "z": -2.292583,
    "visibility": 1.0
  },
  {
    "x": -0.076867,
    "y": -0.982674,
    "z": -2.296293,
    "visibility": 1.0
  },
  {
    "x": -0.111905,
    "y": -0.984768,
    "z": -2.298018,
    "visibility": 1.0
  },
  {
    "x": 0.216098,
    "y": -0.933599,
    "z": -1.265303,
    "visibility": 1.0
  },
  {
    "x": -0.188434,
    "y": -0.963162,
    "z": -1.474374,
    "visibility": 1.0
  },
  {
    "x": 0.10455,
    "y": -0.826935,
    "z": -2.006865,
    "visibility": 1.0
  },
  {
    "x": -0.047563,
    "y": -0.841743,
    "z": -2.087446,
    "visibility": 1.0
  },
  {
    "x": 0.486952,
    "y": -0.484523,
    "z": -0.722233,
    "visibility": 1.0
  },
  {
    "x": -0.608261,
    "y": -0.515477,
    "z": -0.784945,
    "visibility": 1.0
  },
  {
    "x": 0.693823,
    "y": 0.055378,
    "z": -0.260227,
    "visibility": 0.968
  },
  {
    "x": -0.740421,
    "y": 0.070183,
    "z": -0.619883,
    "visibility": 0.9784
  },
  {
    "x": 1.023346,
    "y": 0.445747,
    "z": -0.740659,
    "visibility": 0.9797
  },
  {
    "x": -0.788197,
    "y": 0.591097,
    "z": -1.275693,
    "visibility": 0.9927
  },
  {
    "x": 1.133149,
    "y": 0.593192,
    "z": -0.850552,
    "visibility": 0.9677
  },
  {
    "x": -0.850381,
    "y": 0.740584,
    "z": -1.453358,
    "visibility": 0.987
  },
  {
    "x": 1.167638,
    "y": 0.588405,
    "z": -1.19354,
    "visibility": 0.9729
  },
  {
    "x": -0.818594,
    "y": 0.75403,
    "z": -1.769932,
    "visibility": 0.9887
  },
  {
    "x": 1.112343,
    "y": 0.546677,
    "z": -0.877007,
    "visibility": 0.9706
  },
  {
    "x": -0.75306,
    "y": 0.708565,
    "z": -1.421499,
    "visibility": 0.9868
  },
  {
    "x": 0.367425,
    "y": 0.474884,
    "z": -0.035939,
    "visibility": 1.0
  },
  {
    "x": -0.246117,
    "y": 0.525116,
    "z": 0.031867,
    "visibility": 1.0
  },
  {
    "x": 0.345259,
    "y": 1.407246,
    "z": -0.244667,
    "visibility": 0.9635
  },
  {
    "x": -0.1149,
    "y": 1.440107,
    "z": -0.357662,
    "visibility": 0.9302
  },
  {
    "x": 0.193195,
    "y": 2.27544,
    "z": 0.553503,
    "visibility": 0.9679
  },
  {
    "x": -0.014363,
    "y": 2.146523,
    "z": 0.910035,
    "visibility": 0.9443
  },
  {
    "x": 0.171288,
    "y": 2.32971,
    "z": 0.5761,
    "visibility": 0.6953
  },
  {
    "x": 0.05178,
    "y": 2.198539,
    "z": 1.011125,
    "visibility": 0.6323
  },
  {
    "x": -0.002961,
    "y": 2.666075,
    "z": -0.46234,
    "visibility": 0.9648
  },
  {
    "x": -0.065104,
    "y": 2.527702,
    "z": 0.179621,
    "visibility": 0.9362
  }
]